{"cameraMode":{"drawMode":0,"name":"Shaded","section":"Shading Mode"},"sceneLighting":true,"audioPlay":false,"sceneViewState":{"m_AlwaysRefresh":false,"showFog":true,"showSkybox":true,"showFlares":true,"showImageEffects":true,"showParticleSystems":true,"showVisualEffectGraphs":true,"m_FxEnabled":true},"in2DMode":false,"pivot":{"x":64.96717071533203,"y":-61.12324523925781,"z":-19.55550765991211},"rotation":{"x":0.2606021761894226,"y":0.6683794260025024,"z":-0.2714831531047821,"w":0.6416446566581726},"size":52.2382698059082,"orthographic":false}